{
    "nodes": [
        {
            "id": "2023003.0",
            "课程名称": "技术创新管理",
            "院系": "管理学院",
            "category": "管理学院",
            "课程性质": "专业选修课",
            "课程体系": "nan",
            "是否允许外院选课": "nan",
            "上课语言": "中文"
        },
        {
            "id": "2041514.0",
            "课程名称": "文献阅读与论文导写",
            "院系": "管理学院",
            "category": "管理学院",
            "课程性质": "专业学位课",
            "课程体系": "专业学位",
            "是否允许外院选课": "专业学位",
            "上课语言": "中文"
        },
        {
            "id": "2043506.0",
            "课程名称": "财务分析与预测",
            "院系": "管理学院",
            "category": "管理学院",
            "课程性质": "专业选修课",
            "课程体系": "nan",
            "是否允许外院选课": "nan",
            "上课语言": "全外文"
        },
        {
            "id": "2043526.0",
            "课程名称": "销售队伍管理",
            "院系": "管理学院",
            "category": "管理学院",
            "课程性质": "专业选修课",
            "课程体系": "nan",
            "是否允许外院选课": "nan",
            "上课语言": "中文"
        },
        {
            "id": "2043562.0",
            "课程名称": "国际运营和采购",
            "院系": "管理学院",
            "category": "管理学院",
            "课程性质": "专业选修课",
            "课程体系": "nan",
            "是否允许外院选课": "nan",
            "上课语言": "中文"
        },
        {
            "id": "2041509.0",
            "课程名称": "运营管理",
            "院系": "管理学院",
            "category": "管理学院",
            "课程性质": "专业学位课",
            "课程体系": "专业学位",
            "是否允许外院选课": "专业学位",
            "上课语言": "中文"
        },
        {
            "id": "2043503.0",
            "课程名称": "企业税务筹划",
            "院系": "管理学院",
            "category": "管理学院",
            "课程性质": "专业选修课",
            "课程体系": "nan",
            "是否允许外院选课": "nan",
            "上课语言": "中文"
        },
        {
            "id": "2043509.0",
            "课程名称": "国际创业【英】",
            "院系": "管理学院",
            "category": "管理学院",
            "课程性质": "专业选修课",
            "课程体系": "nan",
            "是否允许外院选课": "nan",
            "上课语言": "全外文"
        },
        {
            "id": "2043520.0",
            "课程名称": "供应链管理战略和现代物流优化",
            "院系": "管理学院",
            "category": "管理学院",
            "课程性质": "专业选修课",
            "课程体系": "nan",
            "是否允许外院选课": "nan",
            "上课语言": "中文"
        },
        {
            "id": "2043522.0",
            "课程名称": "网络营销",
            "院系": "管理学院",
            "category": "管理学院",
            "课程性质": "专业选修课",
            "课程体系": "nan",
            "是否允许外院选课": "nan",
            "上课语言": "中文"
        },
        {
            "id": "2043533.0",
            "课程名称": "国际商务",
            "院系": "管理学院",
            "category": "管理学院",
            "课程性质": "专业选修课",
            "课程体系": "专业学位",
            "是否允许外院选课": "专业学位",
            "上课语言": "双语"
        },
        {
            "id": "2043552.0",
            "课程名称": "商务实践",
            "院系": "管理学院",
            "category": "管理学院",
            "课程性质": "专业选修课",
            "课程体系": "nan",
            "是否允许外院选课": "nan",
            "上课语言": "中文"
        },
        {
            "id": "2043556.0",
            "课程名称": "系统思考与表达",
            "院系": "管理学院",
            "category": "管理学院",
            "课程性质": "专业选修课",
            "课程体系": "nan",
            "是否允许外院选课": "nan",
            "上课语言": "中文"
        },
        {
            "id": "2043563.0",
            "课程名称": "商务实践2",
            "院系": "管理学院",
            "category": "管理学院",
            "课程性质": "专业选修课",
            "课程体系": "nan",
            "是否允许外院选课": "nan",
            "上课语言": "中文"
        },
        {
            "id": "2041510.0",
            "课程名称": "战略管理",
            "院系": "管理学院",
            "category": "管理学院",
            "课程性质": "专业学位课",
            "课程体系": "专业学位",
            "是否允许外院选课": "专业学位",
            "上课语言": "中文"
        },
        {
            "id": "2041517.0",
            "课程名称": "创新与变革管理",
            "院系": "管理学院",
            "category": "管理学院",
            "课程性质": "专业学位课",
            "课程体系": "专业学位",
            "是否允许外院选课": "专业学位",
            "上课语言": "中文"
        },
        {
            "id": "2043207.0",
            "课程名称": "投资学",
            "院系": "管理学院",
            "category": "管理学院",
            "课程性质": "专业选修课",
            "课程体系": "专业学位",
            "是否允许外院选课": "专业学位",
            "上课语言": "中文"
        },
        {
            "id": "2043564.0",
            "课程名称": "为商通说",
            "院系": "管理学院",
            "category": "管理学院",
            "课程性质": "专业选修课",
            "课程体系": "专业学位",
            "是否允许外院选课": "专业学位",
            "上课语言": "中文"
        },
        {
            "id": "2041522.0",
            "课程名称": "公司财务",
            "院系": "管理学院",
            "category": "管理学院",
            "课程性质": "专业学位课",
            "课程体系": "专业学位",
            "是否允许外院选课": "专业学位",
            "上课语言": "中文"
        },
        {
            "id": "2041523.0",
            "课程名称": "管理会计",
            "院系": "管理学院",
            "category": "管理学院",
            "课程性质": "专业学位课",
            "课程体系": "专业学位",
            "是否允许外院选课": "专业学位",
            "上课语言": "中文"
        },
        {
            "id": "2043507.0",
            "课程名称": "股票投资",
            "院系": "管理学院",
            "category": "管理学院",
            "课程性质": "专业选修课",
            "课程体系": "专业学位",
            "是否允许外院选课": "专业学位",
            "上课语言": "双语"
        },
        {
            "id": "2043511.0",
            "课程名称": "创业投资",
            "院系": "管理学院",
            "category": "管理学院",
            "课程性质": "专业选修课",
            "课程体系": "nan",
            "是否允许外院选课": "nan",
            "上课语言": "中文"
        }
    ],
    "links": [
        {
            "source": "2023003.0",
            "target": "2041514.0"
        },
        {
            "source": "2041514.0",
            "target": "2043506.0"
        },
        {
            "source": "2041514.0",
            "target": "2043526.0"
        },
        {
            "source": "2041514.0",
            "target": "2043562.0"
        },
        {
            "source": "2041514.0",
            "target": "2041509.0"
        },
        {
            "source": "2041514.0",
            "target": "2043503.0"
        },
        {
            "source": "2041514.0",
            "target": "2043509.0"
        },
        {
            "source": "2041514.0",
            "target": "2043520.0"
        },
        {
            "source": "2041514.0",
            "target": "2043522.0"
        },
        {
            "source": "2041514.0",
            "target": "2043533.0"
        },
        {
            "source": "2041514.0",
            "target": "2043552.0"
        },
        {
            "source": "2041514.0",
            "target": "2043556.0"
        },
        {
            "source": "2041514.0",
            "target": "2043563.0"
        },
        {
            "source": "2041510.0",
            "target": "2041517.0"
        },
        {
            "source": "2043207.0",
            "target": "2041509.0"
        },
        {
            "source": "2041509.0",
            "target": "2043506.0"
        },
        {
            "source": "2041509.0",
            "target": "2043564.0"
        },
        {
            "source": "2041509.0",
            "target": "2041522.0"
        },
        {
            "source": "2041509.0",
            "target": "2041523.0"
        },
        {
            "source": "2041509.0",
            "target": "2043507.0"
        },
        {
            "source": "2041509.0",
            "target": "2043511.0"
        }
    ],
    "categories": [
        {
            "name": "管理学院"
        }
    ]
}